odoo/addons/repair_order_product_by_lot/README.rst
odoo/addons/repair_order_product_by_lot/__init__.py
odoo/addons/repair_order_product_by_lot/__manifest__.py
odoo/addons/repair_order_product_by_lot/i18n/it.po
odoo/addons/repair_order_product_by_lot/i18n/repair_order_product_by_lot.pot
odoo/addons/repair_order_product_by_lot/models/__init__.py
odoo/addons/repair_order_product_by_lot/models/repair_order.py
odoo/addons/repair_order_product_by_lot/readme/CONTEXT.md
odoo/addons/repair_order_product_by_lot/readme/CONTRIBUTORS.md
odoo/addons/repair_order_product_by_lot/readme/DESCRIPTION.md
odoo/addons/repair_order_product_by_lot/readme/USAGE.md
odoo/addons/repair_order_product_by_lot/readme/newsfragments/.gitkeep
odoo/addons/repair_order_product_by_lot/static/description/icon.png
odoo/addons/repair_order_product_by_lot/static/description/icon.svg
odoo/addons/repair_order_product_by_lot/static/description/index.html
odoo/addons/repair_order_product_by_lot/tests/__init__.py
odoo/addons/repair_order_product_by_lot/tests/test_repair_order_product_by_lot.py
odoo/addons/repair_order_product_by_lot/views/repair_order_views.xml
odoo_addon_repair_order_product_by_lot-18.0.1.0.0.4.dist-info/METADATA
odoo_addon_repair_order_product_by_lot-18.0.1.0.0.4.dist-info/WHEEL
odoo_addon_repair_order_product_by_lot-18.0.1.0.0.4.dist-info/top_level.txt
odoo_addon_repair_order_product_by_lot-18.0.1.0.0.4.dist-info/RECORD
